netbox_cisco_ise/__init__.py
netbox_cisco_ise/ise_client.py
netbox_cisco_ise/navigation.py
netbox_cisco_ise/urls.py
netbox_cisco_ise/views.py
netbox_cisco_ise/templates/netbox_cisco_ise/endpoint_tab.html
netbox_cisco_ise/templates/netbox_cisco_ise/nad_tab.html
netbox_cisco_ise/templates/netbox_cisco_ise/settings.html
netbox_cisco_ise-0.1.4.dist-info/licenses/LICENSE
netbox_cisco_ise-0.1.4.dist-info/METADATA
netbox_cisco_ise-0.1.4.dist-info/WHEEL
netbox_cisco_ise-0.1.4.dist-info/top_level.txt
netbox_cisco_ise-0.1.4.dist-info/RECORD
