Metadata-Version: 2.4
Name: netbox-cisco-ise
Version: 0.1.4
Summary: NetBox plugin for Cisco ISE integration - endpoint tracking, NAD management, and session visibility
Author-email: sieteunoseis <jeremy.worden@gmail.com>
License: Apache-2.0
Project-URL: Homepage, https://github.com/sieteunoseis/netbox-cisco-ise
Project-URL: Repository, https://github.com/sieteunoseis/netbox-cisco-ise
Project-URL: Issues, https://github.com/sieteunoseis/netbox-cisco-ise/issues
Project-URL: Documentation, https://github.com/sieteunoseis/netbox-cisco-ise/wiki
Keywords: netbox,cisco,ise,identity-services-engine,radius,tacacs,nac,endpoint,plugin
Classifier: Development Status :: 3 - Alpha
Classifier: Framework :: Django
Classifier: Intended Audience :: System Administrators
Classifier: License :: OSI Approved :: Apache Software License
Classifier: Programming Language :: Python :: 3
Classifier: Programming Language :: Python :: 3.10
Classifier: Programming Language :: Python :: 3.11
Classifier: Programming Language :: Python :: 3.12
Requires-Python: >=3.10
License-File: LICENSE
Requires-Dist: requests>=2.28.0
Provides-Extra: dev
Requires-Dist: black; extra == "dev"
Requires-Dist: flake8; extra == "dev"
Requires-Dist: isort; extra == "dev"
Requires-Dist: pytest; extra == "dev"
Requires-Dist: pytest-django; extra == "dev"
Requires-Dist: responses; extra == "dev"
Dynamic: license-file
